{
  "port": "XorgBase-Main",
  "name": "Xorg-Server",
  "version": "21.1.14",
  "architectures": ["x86_64"],
  "description": "X server",
  "website": "https://gitlab.freedesktop.org/xorg/xserver",
  "installedFiles": [],
  "dependencies": [
    {
      "port": "GraphicsLibraries-Main",
      "name": "Pixman",
      "version": ">=0.42.2",
      "options": []
    },
    {
      "port": "XorgBase-Main",
      "name": "Xorg-Fonts",
      "version": ">=21.1.8",
      "options": ["Font-Util"]
    },
    {
      "port": "XorgBase-Main",
      "name": "Xkeyboard-Config",
      "version": ">=2.39.0",
      "options": []
    },
    {
      "port": "GraphicsLibraries-Main",
      "name": "Libxcvt",
      "version": ">=0.1.2",
      "options": []
    }
  ],
  "kernelDependencies": [],
  "options": [
    {
      "name": "Elogind",
      "description": "Enable elogind support",
      "active": true,
      "dependencies": [
        {
          "port": "Utilities-Main",
          "name": "Elogind",
          "version": "252.9.0",
          "options": ["Linux-Pam","Polkit"]
        }
      ],
      "kernelDependencies": []
    },
    {
      "name": "Libepoxy",
      "description": "Enable libepoxy support needed for glamor",
      "active": false,
      "dependencies": [
        {
          "port": "GraphicsLibraries-Main",
          "name": "Libepoxy",
          "version": ">=1.5.10",
          "options": []
        }
      ],
      "kernelDependencies": []
    },
    {
      "name": "Libtirpc",
      "description": "Enable libtirpc support",
      "active": false,
      "dependencies": [
        {
          "port": "NetworkingLibraries-Main",
          "name": "Libtirpc",
          "version": ">=1.3.3",
          "options": []
        }
      ],
      "kernelDependencies": []
    },
    {
      "name": "LibXdmcp",
      "description": "Enable libXdmcp support",
      "active": false,
      "dependencies": [
        {
          "port": "GraphicsLibraries-Main",
          "name": "LibXdmcp",
          "version": ">=1.1.4",
          "options": []
        }
      ],
      "kernelDependencies": []
    },
    {
      "name": "Xwayland",
      "description": "Enable xwayland support",
      "active": true,
      "dependencies": [
        {
          "port": "XorgBase-Main",
          "name": "Xwayland",
          "version": ">=23.2.0",
          "options": []
        }
      ],
      "kernelDependencies": []
    },
    {
      "name": "Xf86-Input-Libinput",
      "description": "Enable xf86-input-libinput support",
      "active": false,
      "dependencies": [
        {
          "port": "InputDrivers-Main",
          "name": "Xf86-Input-Libinput",
          "version": ">=1.3.0",
          "options": []
        }
      ],
      "kernelDependencies": []
    },
    {
      "name": "Acpid",
      "description": "Enable acpid support",
      "active": true,
      "dependencies": [
        {
          "port": "Utilities-Main",
          "name": "Acpid",
          "version": ">=2.0.34",
          "options": []
        }
      ],
      "kernelDependencies": []
    },
    {
      "name": "Libunwind",
      "description": "Enable libunwind support",
      "active": false,
      "dependencies": [
        {
          "port": "GraphicsLibraries-Main",
          "name": "Libunwind",
          "version": ">=1.6.2",
          "options": []
        }
      ],
      "kernelDependencies": []
    },
    {
      "name": "Nettle",
      "description": "Enable nettle support",
      "active": false,
      "dependencies": [
        {
          "port": "SecurityLibraries-Main",
          "name": "Nettle",
          "version": ">=3.9.1",
          "options": []
        }
      ],
      "kernelDependencies": []
    },
    {
      "name": "Libgcrypt",
      "description": "Enable libgcrypt support",
      "active": false,
      "dependencies": [
        {
          "port": "SecurityLibraries-Main",
          "name": "Libgcrypt",
          "version": ">=1.10.2",
          "options": []
        }
      ],
      "kernelDependencies": []
    },
    {
      "name": "Xcb-Util-Keysyms",
      "description": "Enable xcb-util-keysyms support",
      "active": false,
      "dependencies": [
        {
          "port": "GraphicsLibraries-Main",
          "name": "Xcb-Util-Keysyms",
          "version": ">=0.4.1",
          "options": []
        }
      ],
      "kernelDependencies": []
    },
    {
      "name": "Xcb-Util-Image",
      "description": "Enable xcb-util-image support",
      "active": false,
      "dependencies": [
        {
          "port": "GraphicsLibraries-Main",
          "name": "Xcb-Util-Image",
          "version": ">=0.4.1",
          "options": []
        }
      ],
      "kernelDependencies": []
    },
    {
      "name": "Xcb-Util-Renderutil",
      "description": "Enable xcb-util-renderutil support",
      "active": false,
      "dependencies": [
        {
          "port": "GraphicsLibraries-Main",
          "name": "Xcb-Util-Renderutil",
          "version": ">=0.3.10",
          "options": []
        }
      ],
      "kernelDependencies": []
    },
    {
      "name": "Xcb-Util-Wm",
      "description": "Enable xcb-util-Wm support",
      "active": false,
      "dependencies": [
        {
          "port": "GraphicsLibraries-Main",
          "name": "Xcb-Util-Wm",
          "version": ">=0.4.2",
          "options": []
        }
      ],
      "kernelDependencies": []
    }
  ],
  "uniqueDependencies": [],
  "uniqueOptions": [],
  "selectedDependencies": [],
  "allowCodependencies": ["@InputDrivers-Main:Xf86-Input-Libinput"]
}
